README.md
setup.py
bitsbehumble/__init__.py
bitsbehumble/source.py
bitsbehumble.egg-info/PKG-INFO
bitsbehumble.egg-info/SOURCES.txt
bitsbehumble.egg-info/dependency_links.txt
bitsbehumble.egg-info/top_level.txt