Metadata-Version: 2.1
Name: bitsbehumble
Version: 0.6
Summary: UNKNOWN
Home-page: https://github.com/AlyaGomaa/bitsbehumble
Author: Alya Gomaa
License: UNKNOWN
Download-URL: https://github.com/AlyaGomaa/bitsbehumble/releases/tag/v-2.0.01
Keywords: CTF,Converter
Platform: UNKNOWN
Classifier: Development Status :: 4 - Beta
Classifier: Intended Audience :: Developers
Classifier: Topic :: Software Development :: Build Tools
Classifier: Programming Language :: Python :: 3
Classifier: Programming Language :: Python :: 3.4
Classifier: Programming Language :: Python :: 3.5
Classifier: Programming Language :: Python :: 3.6
